{
  "competition" : "羽毛球赛事",
  "name of competition" : "羽毛球世界锦标赛",
  "time" : 2017,
  "secretBase" : "Super tower",
  "active" : true,
  "prize winner" : [
    {
      "name" : "贾一凡",
      "age" : 21,
      "awards" : "女双冠军",
      "awardsreceived" : [
        "2013年亚洲青年羽毛球锦标赛女双冠军",
        "2015年中国羽毛球大师赛女双四强",
        "2018年雅加达亚运会羽毛球女子团体亚军"
      ]
    },
    {
      "name" : "陈清晨",
      "age" : 21,
      "awards" : "女双冠军",
      "awardsreceived" : [
        "2012年亚洲青年羽毛球锦标赛混双四强",
        "2015年巴西羽毛球大奖赛女双冠军",
        "2016年中国香港羽毛球超级赛女双四强"
      ]
    },
    {
      "name" : "奥原希望",
      "age" : 23,
      "awards" : "女单冠军",
      "awardsreceived" : [
        "2016年全英羽毛球超级赛女单冠军",
        "2015年世界羽联总决赛女单冠军",
        "2017年8月27日格拉斯哥羽毛球世锦赛女单冠军"
      ]
    }
  ]
}